liga/mlflow/__init__.py
liga/mlflow/logger.py
liga/mlflow/registry.py
liga_mlflow-0.3.0.dist-info/METADATA
liga_mlflow-0.3.0.dist-info/WHEEL
liga_mlflow-0.3.0.dist-info/namespace_packages.txt
liga_mlflow-0.3.0.dist-info/top_level.txt
liga_mlflow-0.3.0.dist-info/RECORD
