Metadata-Version: 2.1
Name: liga-mlflow
Version: 0.3.0
Requires-Python: <3.10,>=3.8
Requires-Dist: SQLAlchemy (<2.0.0)
Requires-Dist: liga (<0.4.0,>=0.3.0)
Requires-Dist: mlflow (<2.0.0,>=1.24.0)
